README.md
README.rst
setup.py
BlueDB/__init__.py
BlueDB/blue2.py
BlueDB/blue3.py
bluedb.egg-info/PKG-INFO
bluedb.egg-info/SOURCES.txt
bluedb.egg-info/dependency_links.txt
bluedb.egg-info/top_level.txt