Metadata-Version: 2.1
Name: bluedb
Version: 0.3.0.4
Summary: Like shelves but better...
Home-page: https://github.com/Enderdas/BlueDB
Author: EnderDas
Author-email: TheRealEnderDas@gmail.com
License: UNKNOWN
Platform: UNKNOWN
